azure/mgmt/vmwarecloudsimple/__init__.py
azure/mgmt/vmwarecloudsimple/_configuration.py
azure/mgmt/vmwarecloudsimple/_vmware_cloud_simple_client.py
azure/mgmt/vmwarecloudsimple/version.py
azure/mgmt/vmwarecloudsimple/models/__init__.py
azure/mgmt/vmwarecloudsimple/models/_models.py
azure/mgmt/vmwarecloudsimple/models/_models_py3.py
azure/mgmt/vmwarecloudsimple/models/_paged_models.py
azure/mgmt/vmwarecloudsimple/models/_vmware_cloud_simple_client_enums.py
azure/mgmt/vmwarecloudsimple/operations/__init__.py
azure/mgmt/vmwarecloudsimple/operations/_customization_policies_operations.py
azure/mgmt/vmwarecloudsimple/operations/_dedicated_cloud_nodes_operations.py
azure/mgmt/vmwarecloudsimple/operations/_dedicated_cloud_services_operations.py
azure/mgmt/vmwarecloudsimple/operations/_operations.py
azure/mgmt/vmwarecloudsimple/operations/_private_clouds_operations.py
azure/mgmt/vmwarecloudsimple/operations/_resource_pools_operations.py
azure/mgmt/vmwarecloudsimple/operations/_skus_availability_operations.py
azure/mgmt/vmwarecloudsimple/operations/_usages_operations.py
azure/mgmt/vmwarecloudsimple/operations/_virtual_machine_templates_operations.py
azure/mgmt/vmwarecloudsimple/operations/_virtual_machines_operations.py
azure/mgmt/vmwarecloudsimple/operations/_virtual_networks_operations.py
azure_mgmt_vmwarecloudsimple-0.2.0.dist-info/METADATA
azure_mgmt_vmwarecloudsimple-0.2.0.dist-info/WHEEL
azure_mgmt_vmwarecloudsimple-0.2.0.dist-info/top_level.txt
azure_mgmt_vmwarecloudsimple-0.2.0.dist-info/RECORD
